{
  "updated_at": "2026-06-17T15:06:03.691Z",
  "workstations": [
    {
      "id": "PL-1-1",
      "line_number": 1,
      "station_number": 1,
      "label": "PL1 · Machine 1",
      "x": 48,
      "y": 65,
      "machine_use": null,
      "machine_reference": null
    },
    {
      "id": "PL-1-2",
      "line_number": 1,
      "station_number": 2,
      "label": "PL1 · Machine 2",
      "x": 48,
      "y": 61.3,
      "machine_use": null,
      "machine_reference": null
    },
    {
      "id": "PL-1-3",
      "line_number": 1,
      "station_number": 3,
      "label": "PL1 · Machine 3",
      "x": 48,
      "y": 57.5,
      "machine_use": null,
      "machine_reference": null
    },
    {
      "id": "PL-1-4",
      "line_number": 1,
      "station_number": 4,
      "label": "PL1 · Machine 4",
      "x": 48,
      "y": 53.8,
      "machine_use": null,
      "machine_reference": null
    },
    {
      "id": "PL-1-5",
      "line_number": 1,
      "station_number": 5,
      "label": "PL1 · Machine 5",
      "x": 48,
      "y": 50,
      "machine_use": null,
      "machine_reference": null
    },
    {
      "id": "PL-1-6",
      "line_number": 1,
      "station_number": 6,
      "label": "PL1 · Machine 6",
      "x": 48,
      "y": 46.3,
      "machine_use": null,
      "machine_reference": null
    },
    {
      "id": "PL-1-7",
      "line_number": 1,
      "station_number": 7,
      "label": "PL1 · Machine 7",
      "x": 48,
      "y": 42.5,
      "machine_use": null,
      "machine_reference": null
    },
    {
      "id": "PL-1-8",
      "line_number": 1,
      "station_number": 8,
      "label": "PL1 · Machine 8",
      "x": 48,
      "y": 38.8,
      "machine_use": null,
      "machine_reference": null
    },
    {
      "id": "PL-1-9",
      "line_number": 1,
      "station_number": 9,
      "label": "PL1 · Machine 9",
      "x": 48,
      "y": 35,
      "machine_use": null,
      "machine_reference": null
    },
    {
      "id": "PL-2-1",
      "line_number": 2,
      "station_number": 1,
      "label": "PL2 · Machine 1",
      "x": 54,
      "y": 65,
      "machine_use": "ZHE JIANG Sote Sewing Machine",
      "machine_reference": "ST-360L"
    },
    {
      "id": "PL-2-2",
      "line_number": 2,
      "station_number": 2,
      "label": "PL2 · Machine 2",
      "x": 54,
      "y": 61.3,
      "machine_use": "ELASTIC Machine Belt",
      "machine_reference": "JK-8009VCDi-12064PR"
    },
    {
      "id": "PL-2-3",
      "line_number": 2,
      "station_number": 3,
      "label": "PL2 · Machine 3",
      "x": 54,
      "y": 57.5,
      "machine_use": "Joining Machine OVER COAT",
      "machine_reference": "ST-313L"
    },
    {
      "id": "PL-2-4",
      "line_number": 2,
      "station_number": 4,
      "label": "PL2 · Machine 4",
      "x": 54,
      "y": 53.8,
      "machine_use": "LAPEL Extra fabric Cutting Cutter",
      "machine_reference": "ST-70P"
    },
    {
      "id": "PL-2-5",
      "line_number": 2,
      "station_number": 5,
      "label": "PL2 · Machine 5",
      "x": 54,
      "y": 50,
      "machine_use": null,
      "machine_reference": "ST-103D"
    },
    {
      "id": "PL-2-6",
      "line_number": 2,
      "station_number": 6,
      "label": "PL2 · Machine 6",
      "x": 54,
      "y": 46.3,
      "machine_use": "DOUBLE NEEDLE CHAIN STITCH",
      "machine_reference": "JK-8558G-WZ"
    },
    {
      "id": "PL-2-7",
      "line_number": 2,
      "station_number": 7,
      "label": "PL2 · Machine 7",
      "x": 54,
      "y": 42.5,
      "machine_use": "METAL BUTTON MACHINE",
      "machine_reference": "XD-818D"
    },
    {
      "id": "PL-2-8",
      "line_number": 2,
      "station_number": 8,
      "label": "PL2 · Machine 8",
      "x": 54,
      "y": 38.8,
      "machine_use": "METAL BUTTON MACHINE",
      "machine_reference": "XD-818D"
    },
    {
      "id": "PL-2-9",
      "line_number": 2,
      "station_number": 9,
      "label": "PL2 · Machine 9",
      "x": 54,
      "y": 35,
      "machine_use": "BONE POCKET MACHINE",
      "machine_reference": "ZJAPW-2520-SJ"
    },
    {
      "id": "PL-3-1",
      "line_number": 3,
      "station_number": 1,
      "label": "PL3 · Machine 1",
      "x": 60,
      "y": 65,
      "machine_use": "Pocket Making Machine Trousers",
      "machine_reference": "ZJ-M3-S500-SF-V2"
    },
    {
      "id": "PL-3-2",
      "line_number": 3,
      "station_number": 2,
      "label": "PL3 · Machine 2",
      "x": 60,
      "y": 61.3,
      "machine_use": "Vacuum Table Ironing",
      "machine_reference": "JN-1190P-GH"
    },
    {
      "id": "PL-3-3",
      "line_number": 3,
      "station_number": 3,
      "label": "PL3 · Machine 3",
      "x": 60,
      "y": 57.5,
      "machine_use": "Flat Machine",
      "machine_reference": "KSE-UT-33AB"
    },
    {
      "id": "PL-3-4",
      "line_number": 3,
      "station_number": 4,
      "label": "PL3 · Machine 4",
      "x": 60,
      "y": 53.8,
      "machine_use": "Flat Machine",
      "machine_reference": "KSE-UT-35ACx356/Z"
    },
    {
      "id": "PL-3-5",
      "line_number": 3,
      "station_number": 5,
      "label": "PL3 · Machine 5",
      "x": 60,
      "y": 50,
      "machine_use": "Triple Needle Chain Stitch",
      "machine_reference": "ZJ3800-BD"
    },
    {
      "id": "PL-3-6",
      "line_number": 3,
      "station_number": 6,
      "label": "PL3 · Machine 6",
      "x": 60,
      "y": 46.3,
      "machine_use": "Double Needle Chain Stitch",
      "machine_reference": "ZJ-3830H-P-PLB-J-BD"
    },
    {
      "id": "PL-3-7",
      "line_number": 3,
      "station_number": 7,
      "label": "PL3 · Machine 7",
      "x": 60,
      "y": 42.5,
      "machine_use": "Elastic Machine",
      "machine_reference": "JK-8009VC-04064PR/WL"
    },
    {
      "id": "PL-3-8",
      "line_number": 3,
      "station_number": 8,
      "label": "PL3 · Machine 8",
      "x": 60,
      "y": 38.8,
      "machine_use": "Double Needle Machine",
      "machine_reference": "ZJ-2875PA-5-BD-B3-AF-3/02"
    },
    {
      "id": "PL-3-9",
      "line_number": 3,
      "station_number": 9,
      "label": "PL3 · Machine 9",
      "x": 60,
      "y": 35,
      "machine_use": null,
      "machine_reference": null
    },
    {
      "id": "PL-4-1",
      "line_number": 4,
      "station_number": 1,
      "label": "PL4 · Machine 1",
      "x": 66,
      "y": 65,
      "machine_use": "Fedo Machine",
      "machine_reference": "JK-T9270D-12-2PL"
    },
    {
      "id": "PL-4-2",
      "line_number": 4,
      "station_number": 2,
      "label": "PL4 · Machine 2",
      "x": 66,
      "y": 61.3,
      "machine_use": "Coller Adjustment Machine",
      "machine_reference": "EW-2000-02"
    },
    {
      "id": "PL-4-3",
      "line_number": 4,
      "station_number": 3,
      "label": "PL4 · Machine 3",
      "x": 66,
      "y": 57.5,
      "machine_use": "Stitching Machine",
      "machine_reference": "DDL-5550"
    },
    {
      "id": "PL-4-4",
      "line_number": 4,
      "station_number": 4,
      "label": "PL4 · Machine 4",
      "x": 66,
      "y": 53.8,
      "machine_use": "Stitching Machine",
      "machine_reference": "288A00349"
    },
    {
      "id": "PL-4-5",
      "line_number": 4,
      "station_number": 5,
      "label": "PL4 · Machine 5",
      "x": 66,
      "y": 50,
      "machine_use": "Stitching Machine",
      "machine_reference": "ASE-A"
    },
    {
      "id": "PL-4-6",
      "line_number": 4,
      "station_number": 6,
      "label": "PL4 · Machine 6",
      "x": 66,
      "y": 46.3,
      "machine_use": "Stitching Machine",
      "machine_reference": "ASE-A"
    },
    {
      "id": "PL-4-7",
      "line_number": 4,
      "station_number": 7,
      "label": "PL4 · Machine 7",
      "x": 66,
      "y": 42.5,
      "machine_use": "Stitching Machine",
      "machine_reference": "ASE-A"
    },
    {
      "id": "PL-4-8",
      "line_number": 4,
      "station_number": 8,
      "label": "PL4 · Machine 8",
      "x": 66,
      "y": 38.8,
      "machine_use": "Stitching Machine",
      "machine_reference": "ASE-A"
    },
    {
      "id": "PL-4-9",
      "line_number": 4,
      "station_number": 9,
      "label": "PL4 · Machine 9",
      "x": 66,
      "y": 35,
      "machine_use": null,
      "machine_reference": null
    },
    {
      "id": "PL-5-1",
      "line_number": 5,
      "station_number": 1,
      "label": "PL5 · Machine 1",
      "x": 71,
      "y": 65,
      "machine_use": "POCKET Ironing Plant",
      "machine_reference": "TB-58"
    },
    {
      "id": "PL-5-2",
      "line_number": 5,
      "station_number": 2,
      "label": "PL5 · Machine 2",
      "x": 71,
      "y": 61.3,
      "machine_use": "Vaccum Table Ironing",
      "machine_reference": "JN-1190J-GH"
    },
    {
      "id": "PL-5-3",
      "line_number": 5,
      "station_number": 3,
      "label": "PL5 · Machine 3",
      "x": 71,
      "y": 57.5,
      "machine_use": "Vaccum Table Ironing",
      "machine_reference": "JN-VBSH-P"
    },
    {
      "id": "PL-5-4",
      "line_number": 5,
      "station_number": 4,
      "label": "PL5 · Machine 4",
      "x": 71,
      "y": 53.8,
      "machine_use": "Stitching Machine",
      "machine_reference": "ASE-A"
    },
    {
      "id": "PL-5-5",
      "line_number": 5,
      "station_number": 5,
      "label": "PL5 · Machine 5",
      "x": 71,
      "y": 50,
      "machine_use": "Stitching Machine",
      "machine_reference": "ASE-A"
    },
    {
      "id": "PL-5-6",
      "line_number": 5,
      "station_number": 6,
      "label": "PL5 · Machine 6",
      "x": 71,
      "y": 46.3,
      "machine_use": "Stitching Machine",
      "machine_reference": "ASE-A"
    },
    {
      "id": "PL-5-7",
      "line_number": 5,
      "station_number": 7,
      "label": "PL5 · Machine 7",
      "x": 71,
      "y": 42.5,
      "machine_use": "Stitching Machine",
      "machine_reference": "ASE-A"
    },
    {
      "id": "PL-5-8",
      "line_number": 5,
      "station_number": 8,
      "label": "PL5 · Machine 8",
      "x": 71,
      "y": 38.8,
      "machine_use": "Stitching Machine",
      "machine_reference": "A9200L-D4S-W-CP/02"
    },
    {
      "id": "PL-5-9",
      "line_number": 5,
      "station_number": 9,
      "label": "PL5 · Machine 9",
      "x": 71,
      "y": 35,
      "machine_use": null,
      "machine_reference": null
    },
    {
      "id": "PL-6-1",
      "line_number": 6,
      "station_number": 1,
      "label": "PL6 · Machine 1",
      "x": 77,
      "y": 65,
      "machine_use": "Trial Showing Thread Machine",
      "machine_reference": "HT-1000"
    },
    {
      "id": "PL-6-2",
      "line_number": 6,
      "station_number": 2,
      "label": "PL6 · Machine 2",
      "x": 77,
      "y": 61.3,
      "machine_use": "Safty over lock",
      "machine_reference": "B9500-70-02"
    },
    {
      "id": "PL-6-3",
      "line_number": 6,
      "station_number": 3,
      "label": "PL6 · Machine 3",
      "x": 77,
      "y": 57.5,
      "machine_use": "Stitching Machine",
      "machine_reference": "ASE-A"
    },
    {
      "id": "PL-6-4",
      "line_number": 6,
      "station_number": 4,
      "label": "PL6 · Machine 4",
      "x": 77,
      "y": 53.8,
      "machine_use": "Stitching Machine",
      "machine_reference": "ASE-A"
    },
    {
      "id": "PL-6-5",
      "line_number": 6,
      "station_number": 5,
      "label": "PL6 · Machine 5",
      "x": 77,
      "y": 50,
      "machine_use": "Stitching Machine",
      "machine_reference": "ASE-A"
    },
    {
      "id": "PL-6-6",
      "line_number": 6,
      "station_number": 6,
      "label": "PL6 · Machine 6",
      "x": 77,
      "y": 46.3,
      "machine_use": "Stitching Machine",
      "machine_reference": "A9200L-D4S-W-CP/02"
    },
    {
      "id": "PL-6-7",
      "line_number": 6,
      "station_number": 7,
      "label": "PL6 · Machine 7",
      "x": 77,
      "y": 42.5,
      "machine_use": "Stitching Machine",
      "machine_reference": "ASE-A"
    },
    {
      "id": "PL-6-8",
      "line_number": 6,
      "station_number": 8,
      "label": "PL6 · Machine 8",
      "x": 77,
      "y": 38.8,
      "machine_use": "Inerbelt Stitching Machine",
      "machine_reference": "FX-160-20"
    },
    {
      "id": "PL-6-9",
      "line_number": 6,
      "station_number": 9,
      "label": "PL6 · Machine 9",
      "x": 77,
      "y": 35,
      "machine_use": null,
      "machine_reference": null
    },
    {
      "id": "PL-7-1",
      "line_number": 7,
      "station_number": 1,
      "label": "PL7 · Machine 1",
      "x": 83,
      "y": 65,
      "machine_use": "Zigzag Machine",
      "machine_reference": "PI-720-1.3M"
    },
    {
      "id": "PL-7-2",
      "line_number": 7,
      "station_number": 2,
      "label": "PL7 · Machine 2",
      "x": 83,
      "y": 61.3,
      "machine_use": "Zigzag Machine",
      "machine_reference": "20U457-D"
    },
    {
      "id": "PL-7-3",
      "line_number": 7,
      "station_number": 3,
      "label": "PL7 · Machine 3",
      "x": 83,
      "y": 57.5,
      "machine_use": "Vaccum Table Ironing",
      "machine_reference": "JW-VBSP-H"
    },
    {
      "id": "PL-7-4",
      "line_number": 7,
      "station_number": 4,
      "label": "PL7 · Machine 4",
      "x": 83,
      "y": 53.8,
      "machine_use": "Vaccum Table Ironing",
      "machine_reference": "JW-110P-GH"
    },
    {
      "id": "PL-7-5",
      "line_number": 7,
      "station_number": 5,
      "label": "PL7 · Machine 5",
      "x": 83,
      "y": 50,
      "machine_use": "Stitching machine",
      "machine_reference": "DDL-5550"
    },
    {
      "id": "PL-7-6",
      "line_number": 7,
      "station_number": 6,
      "label": "PL7 · Machine 6",
      "x": 83,
      "y": 46.3,
      "machine_use": "Baby overlock",
      "machine_reference": "ZJ-9528-13-BD"
    },
    {
      "id": "PL-7-7",
      "line_number": 7,
      "station_number": 7,
      "label": "PL7 · Machine 7",
      "x": 83,
      "y": 42.5,
      "machine_use": "Lata Machine",
      "machine_reference": "ZJ101-BD"
    },
    {
      "id": "PL-7-8",
      "line_number": 7,
      "station_number": 8,
      "label": "PL7 · Machine 8",
      "x": 83,
      "y": 38.8,
      "machine_use": "Sefty overlock",
      "machine_reference": "MO-6716S"
    },
    {
      "id": "PL-7-9",
      "line_number": 7,
      "station_number": 9,
      "label": "PL7 · Machine 9",
      "x": 83,
      "y": 35,
      "machine_use": null,
      "machine_reference": null
    },
    {
      "id": "PL-8-1",
      "line_number": 8,
      "station_number": 1,
      "label": "PL8 · Machine 1",
      "x": 89,
      "y": 65,
      "machine_use": "Alite Machine Button Hole",
      "machine_reference": "ZJ5821A"
    },
    {
      "id": "PL-8-2",
      "line_number": 8,
      "station_number": 2,
      "label": "PL8 · Machine 2",
      "x": 89,
      "y": 61.3,
      "machine_use": "Arravi Machine Button Hole",
      "machine_reference": "LBH-781"
    },
    {
      "id": "PL-8-3",
      "line_number": 8,
      "station_number": 3,
      "label": "PL8 · Machine 3",
      "x": 89,
      "y": 57.5,
      "machine_use": "Button Machine Shirt",
      "machine_reference": "MB-1373"
    },
    {
      "id": "PL-8-4",
      "line_number": 8,
      "station_number": 4,
      "label": "PL8 · Machine 4",
      "x": 89,
      "y": 53.8,
      "machine_use": "Button Machine",
      "machine_reference": "ZJ1903D-301-3/04-V4"
    },
    {
      "id": "PL-8-5",
      "line_number": 8,
      "station_number": 5,
      "label": "PL8 · Machine 5",
      "x": 89,
      "y": 50,
      "machine_use": "CHAMPA Machine OUT SIDE",
      "machine_reference": "781-E"
    },
    {
      "id": "PL-8-6",
      "line_number": 8,
      "station_number": 6,
      "label": "PL8 · Machine 6",
      "x": 89,
      "y": 46.3,
      "machine_use": "CHAMPA Machine INSIDE",
      "machine_reference": "ZJ200"
    },
    {
      "id": "PL-8-7",
      "line_number": 8,
      "station_number": 7,
      "label": "PL8 · Machine 7",
      "x": 89,
      "y": 42.5,
      "machine_use": "D-BRTAK",
      "machine_reference": "ZJ1900DSS-3/04-V4"
    },
    {
      "id": "PL-8-8",
      "line_number": 8,
      "station_number": 8,
      "label": "PL8 · Machine 8",
      "x": 89,
      "y": 38.8,
      "machine_use": "Lupe Machine",
      "machine_reference": "CM-861D"
    },
    {
      "id": "PL-8-9",
      "line_number": 8,
      "station_number": 9,
      "label": "PL8 · Machine 9",
      "x": 89,
      "y": 35,
      "machine_use": "Lata Machine",
      "machine_reference": "BS-352"
    }
  ]
}
