{
  "updated_at": "2026-06-05T22:49:34.365Z",
  "work_orders": [
    {
      "id": "pwo-cu-86ewefwtq-1",
      "status": "packed",
      "client_id": "cu-ralph-rahme-fouad-rahme",
      "so_number": "SO-2026-0071",
      "piece_name": "Trouser",
      "updated_at": "2026-06-05T15:37:55.677Z",
      "client_code": "FR-0126-0019",
      "client_name": "Ralph Rahme",
      "received_at": "2026-01-30T20:00:43.651Z",
      "supplier_id": "drapers",
      "completed_at": null,
      "garment_type": "Trouser",
      "sticker_code": "FR-0126-0019-SO-2026-0071-L02-TR",
      "fabric_meters": 1,
      "fabric_number": "71021",
      "supplier_name": "Drapers",
      "sales_order_id": "so-cu-86ewefwtk",
      "fabric_prep_step": null,
      "fabric_prep_type": null,
      "sales_order_line_id": "line-cu-86ewefwtk-1"
    },
    {
      "id": "pwo-cu-86ewefwtk-1",
      "status": "finishing",
      "client_id": "cu-ralph-rahme-fouad-rahme",
      "so_number": "SO-2026-0071",
      "piece_name": "Trouser",
      "updated_at": "2026-05-28T22:28:28.091Z",
      "client_code": "FR-0126-0019",
      "client_name": "Ralph Rahme",
      "received_at": "2026-01-30T20:00:43.256Z",
      "supplier_id": "drapers",
      "completed_at": null,
      "garment_type": "Trouser",
      "sticker_code": "FR-0126-0019-SO-2026-0071-L03-TR",
      "fabric_meters": 1,
      "fabric_number": "71060",
      "supplier_name": "Drapers",
      "sales_order_id": "so-cu-86ewefwtk",
      "fabric_prep_step": null,
      "fabric_prep_type": null,
      "sales_order_line_id": "line-cu-86ewefwtk-2"
    }
  ]
}
